AnkiCardOTron/AnkiCardOTron.py
AnkiCardOTron/__init__.py
AnkiCardOTron/test.py
AnkiOTron-1.2.dist-info/LICENSE
AnkiOTron-1.2.dist-info/METADATA
AnkiOTron-1.2.dist-info/WHEEL
AnkiOTron-1.2.dist-info/top_level.txt
AnkiOTron-1.2.dist-info/RECORD
