Metadata-Version: 2.1
Name: AnkiOTron
Version: 1.2
Summary: Wrapper around genaki to automate Anki deck creation
Home-page: https://github.com/danielpassy/Anki-CardOTron
Author: Daniel de Mattos Passy
Author-email: daniel.passy@gmail.com
License: UNKNOWN
Platform: UNKNOWN
Classifier: Programming Language :: Python :: 3
Classifier: License :: OSI Approved :: MIT License
Classifier: Operating System :: OS Independent
Requires-Python: >=3.6
